{
  "name": "Repair",
  "type": "move",
  "system": {
    "name": "",
    "description": "<p>If a plane has been torn up or broken down and you help the mechanics fix her, roll +skill. On any hit you patch it together and it is no longer damaged. On 7-9 you patch it together but choose two (Protectors choose one):</p>\n<ul>\n<li>She’ll fly eventually, but not tonight</li>\n<li>You take 1-harm from lack of sleep</li>\n<li>You don’t complete the job in the officially approved manner</li>\n<li>The plane acquires a personality if it doesn’t have one already</li>\n</ul>",
    "moveType": "dayMoves",
    "rollFormula": "",
    "moveResults": {
      "failure": {
        "key": "system.moveResults.failure.value",
        "label": "Miss",
        "value": "<p>You are send it into combat still damaged. Maybe that&rsquo;s obvious and maybe it isn&rsquo;t.</p>"
      },
      "partial": {
        "key": "system.moveResults.partial.value",
        "label": "Partial Hit",
        "value": "<p>You patch it together and it is no longer damaged, but choose two (Protectors choose one):</p>\n<ul>\n<li>She&rsquo;ll fly eventually, but not tonight</li>\n<li>You take 1-harm from lack of sleep</li>\n<li>You don&rsquo;t complete the job in the officially approved manner</li>\n<li>The plane acquires a personality if it doesn&rsquo;t have one already</li>\n</ul>"
      },
      "success": {
        "key": "system.moveResults.success.value",
        "label": "Full Hit!",
        "value": "<p>You patch it together and it is no longer damaged.</p>"
      }
    },
    "uses": 0,
    "playbook": "",
    "rollType": "skill",
    "rollMod": 0,
    "choices": "",
    "actorType": "character"
  },
  "_id": "wNwQjru0sIrl6Ltd",
  "img": "icons/svg/upgrade.svg",
  "effects": [],
  "folder": null,
  "sort": 500000,
  "ownership": {
    "default": 0,
    "RvB4EHRfspAUyhGT": 3
  },
  "flags": {},
  "_stats": {
    "systemId": "pbta",
    "systemVersion": "1.0.20",
    "coreVersion": "12.328",
    "createdTime": 1707688549537,
    "modifiedTime": 1720843405584,
    "lastModifiedBy": "g7RaCfWcjdoXToBo",
    "compendiumSource": null,
    "duplicateSource": null
  },
  "_key": "!items!wNwQjru0sIrl6Ltd"
}
